MetReTrim/__init__.py
MetReTrim-0.1.dist-info/DESCRIPTION.rst
MetReTrim-0.1.dist-info/METADATA
MetReTrim-0.1.dist-info/RECORD
MetReTrim-0.1.dist-info/WHEEL
MetReTrim-0.1.dist-info/metadata.json
MetReTrim-0.1.dist-info/top_level.txt
