Metadata-Version: 2.0
Name: MetReTrim
Version: 0.1
Summary: Heterogenous 'N' spacer sequence trimmer
Home-page: https://github.com/Mohak91/MetReTrim
Author: Mohak Sharda
Author-email: sharda.mohak@gmail.com
License: UNKNOWN
Platform: UNKNOWN
Classifier: Programming Language :: Python :: 3
Classifier: License :: OSI Approved :: MIT License
Classifier: Operating System :: OS Independent
